eips/__init__.py
eips/__main__.py
eips/cli.py
eips/const.py
eips/eips.py
eips/enum.py
eips/git.py
eips/logging.py
eips/object.py
eips/parsing.py
eips/util.py
eips-0.2.0.dist-info/METADATA
eips-0.2.0.dist-info/WHEEL
eips-0.2.0.dist-info/entry_points.txt
eips-0.2.0.dist-info/licenses/LICENSE
eips-0.2.0.dist-info/RECORD
