Metadata-Version: 2.3
Name: eips
Version: 0.2.0
Summary: Ethereum Improvement Proposal (EIP) ETL library
Project-URL: source, https://github.com/mikeshultz/eips
Author-email: Mike Shultz <mike@mikeshultz.com>
License: Copyright © 2023 Mike Shultz
Keywords: eip,ethereum,etl
Classifier: Development Status :: 3 - Alpha
Classifier: Intended Audience :: Developers
Classifier: License :: OSI Approved :: MIT License
Classifier: Operating System :: OS Independent
Classifier: Programming Language :: Python :: 3.10
Classifier: Programming Language :: Python :: 3.11
Classifier: Programming Language :: Python :: 3.12
Classifier: Topic :: Software Development :: Libraries :: Python Modules
Classifier: Topic :: Utilities
Requires-Python: >=3.10
Requires-Dist: click~=8.1
Requires-Dist: dulwich~=0.22.4
Requires-Dist: pydantic~=2.9
Requires-Dist: python-dateutil~=2.8.2
Requires-Dist: typing-extensions<5,>=4.0
Provides-Extra: dev
Requires-Dist: hatch-vcs~=0.4.0; extra == 'dev'
Requires-Dist: hatch<2,>=1.13; extra == 'dev'
Requires-Dist: pyright~=1.1.387; extra == 'dev'
Requires-Dist: pytest-cov>=4.1.0; extra == 'dev'
Requires-Dist: pytest>=7.4.2; extra == 'dev'
Requires-Dist: ruff~=0.7.2; extra == 'dev'
